eztransfer/__init__.py
eztransfer/base.py
eztransfer/transfer.py
eztransfer/util.py
eztransfer/handles/__init__.py
eztransfer/handles/azure_blob_storage.py
eztransfer/handles/sftp.py
eztransfer-0.0.1.1.dist-info/LICENSE
eztransfer-0.0.1.1.dist-info/METADATA
eztransfer-0.0.1.1.dist-info/WHEEL
eztransfer-0.0.1.1.dist-info/top_level.txt
eztransfer-0.0.1.1.dist-info/RECORD
