Metadata-Version: 2.1
Name: eztransfer
Version: 0.0.1.1
Summary: Simple tool that makes moving your files between different storage providers easier.
Home-page: https://github.com/mbroton/ez-transfer
Author: Michal Broton
Author-email: michal.broton.ns@gmail.com
License: UNKNOWN
Project-URL: Bug Tracker, https://github.com/mbroton/ez-transfer/issues
Platform: UNKNOWN
Classifier: Programming Language :: Python :: 3
Classifier: License :: OSI Approved :: MIT License
Classifier: Operating System :: OS Independent
Requires-Python: >=3.6
License-File: LICENSE
